chatbot_rag/RAG.py
chatbot_rag/__init__.py
chatbot_rag/chat.py
chatbot_rag/preprocessing.py
chatbot_rag-0.1.8.dist-info/licenses/LICENSE
chatbot_rag-0.1.8.dist-info/METADATA
chatbot_rag-0.1.8.dist-info/WHEEL
chatbot_rag-0.1.8.dist-info/top_level.txt
chatbot_rag-0.1.8.dist-info/RECORD
