Metadata-Version: 2.4
Name: chatbot-rag
Version: 0.1.8
Summary: ChatBot with Retrieval Augmented Generation
Author: Wilhelm David Buitrago Garcia
Project-URL: Homepage, https://github.com/WilhelmBuitrago/ChatBot-RAG.git
Keywords: RAG,ChatBot,Retrieval Augmented Generation,LLM,Language Model,NLP,Natural Language Processing
Classifier: Development Status :: 3 - Alpha
Classifier: Operating System :: OS Independent
Classifier: Programming Language :: Python :: 3
Classifier: Programming Language :: Python :: 3.12
Requires-Python: >=3.12
License-File: LICENSE
Requires-Dist: ollama==0.5.1
Requires-Dist: langchain==0.3.25
Requires-Dist: langchain-community==0.3.24
Requires-Dist: pdfplumber==0.11.6
Requires-Dist: sentence_transformers==4.1.0
Requires-Dist: pymupdf==1.26.0
Requires-Dist: pytesseract==0.3.13
Requires-Dist: faiss-cpu==1.11.0
Requires-Dist: pandas==2.2.3
Dynamic: license-file
